LICENSE.txt
MANIFEST.in
pycl.py
setup.cfg
setup.py
pycl.egg-info/PKG-INFO
pycl.egg-info/SOURCES.txt
pycl.egg-info/dependency_links.txt
pycl.egg-info/entry_points.txt
pycl.egg-info/top_level.txt