Metadata-Version: 1.1
Name: pycl
Version: 0.1.0
Summary: OpenCL wrapper using ctypes
Home-page: https://github.com/ucb-sejits/pycl
Author: Ken Watford
Author-email: kwatford@gmail.com
License: MIT
Download-URL: https://github.com/ucb-sejits/pycl
Platform: UNKNOWN
Classifier: Development Status :: 3 - Alpha
Classifier: License :: OSI Approved :: MIT License
Classifier: Operating System :: OS Independent
Classifier: Topic :: Software Development :: Libraries
Classifier: Programming Language :: Python :: 2
Classifier: Programming Language :: Python :: 3
